{"skeleton":{"hash":"D3N6ec0M/y9aWbqIukOUTCqAUyo","spine":"3.8.99","x":-46.24,"y":-19.15,"width":98,"height":161,"images":"./i/","audio":"D:/TTTTTTTTTTTTT2021/Project_Farm/Working/Gameplay/Tree/Tomato"},"bones":[{"name":"root"},{"name":"Scale","parent":"root"},{"name":"cc_La_4","parent":"Scale","length":17,"rotation":137.36,"x":-13.7,"y":85.5,"color":"0d5500ff"},{"name":"cc_La_1","parent":"Scale","length":21,"rotation":167.08,"x":-0.16,"y":28.99,"color":"6dc98cff"},{"name":"cc_La_7","parent":"Scale","length":21,"rotation":96.6,"x":-3.18,"y":3.1,"color":"0d5500ff"},{"name":"cc_La_8","parent":"Scale","length":69,"rotation":77.83,"x":-2.71,"y":23.55,"color":"df00ffff"},{"name":"cc_Ngo_4","parent":"Scale","length":28,"rotation":92.55,"x":-1.5,"y":75.59,"color":"ff5a5aff"},{"name":"cc_Ngo_1","parent":"Scale","length":26,"rotation":71.39,"x":0.05,"y":2.13,"color":"ff5a5aff"},{"name":"cc_Ngo_2","parent":"Scale","length":17,"rotation":125.21,"x":-10.09,"y":36.22,"color":"ff5a5aff"},{"name":"cc_Ngo_3","parent":"Scale","length":21,"rotation":60.62,"x":13.99,"y":54.08,"color":"ff5a5aff"},{"name":"cc_Body","parent":"Scale","length":91.18,"rotation":90,"x":-0.73,"y":2.01,"color":"197628ff"},{"name":"cc_La_9","parent":"Scale","length":17,"rotation":58.94,"x":4.08,"y":2.01,"color":"0d5500ff"},{"name":"cc_La_2","parent":"Scale","length":21,"rotation":24.09,"x":5.96,"y":52.26,"color":"6dc98cff"},{"name":"cc_La_3","parent":"Scale","length":21,"rotation":57.84,"x":5.82,"y":95.19,"color":"0d5500ff"},{"name":"cc_C1_La","parent":"Scale","length":21,"rotation":168.29,"x":-1.21,"y":61,"color":"6dc98cff"},{"name":"cc_La_56","parent":"Scale","length":15,"x":-0.88,"y":1.64},{"name":"hat_giongA","parent":"Scale","color":"7a7cb3ff"},{"name":"mamA","parent":"hat_giongA","length":39,"rotation":90,"color":"00036dff"}],"slots":[{"name":"hat_giongA","bone":"hat_giongA"},{"name":"mamA","bone":"mamA"},{"name":"cc_La_9","bone":"cc_La_9","attachment":"cc_La_9"},{"name":"cc_La_8","bone":"cc_La_8","attachment":"cc_La_8"},{"name":"cc_La_7","bone":"cc_La_7","attachment":"cc_La_7"},{"name":"cc_Body","bone":"cc_Body","attachment":"cc_Body"},{"name":"cc_La_56","bone":"cc_La_56","attachment":"cc_La_56"},{"name":"cc_La_4","bone":"cc_La_4"},{"name":"cc_La_3","bone":"cc_La_3","attachment":"cc_La_3"},{"name":"cc_Ngo_4","bone":"cc_Ngo_4","attachment":"cc_Ngo_4"},{"name":"cc_Ngo_3","bone":"cc_Ngo_3","attachment":"cc_Ngo_3"},{"name":"cc_La_2","bone":"cc_La_2","attachment":"cc_La_2"},{"name":"cc_Ngo_2","bone":"cc_Ngo_2","attachment":"cc_Ngo_2"},{"name":"cc_La_1","bone":"cc_La_1","attachment":"cc_La_1"},{"name":"cc_Ngo_1","bone":"cc_Ngo_1","attachment":"cc_Ngo_1"},{"name":"cc_C1_La","bone":"cc_C1_La"}],"skins":[{"name":"default","attachments":{"cc_Body":{"cc_Body":{"x":46.33,"y":0.51,"rotation":-90,"width":16,"height":101}},"cc_C1_La":{"cc_C1_La":{"x":17.9,"y":-0.45,"rotation":-168.29,"width":44,"height":23}},"cc_La_1":{"cc_La_1":{"x":21.74,"y":-0.51,"rotation":-167.08,"width":50,"height":25}},"cc_La_2":{"cc_La_2":{"x":21.07,"y":-3.85,"rotation":-24.09,"width":50,"height":25}},"cc_La_3":{"cc_La_3":{"x":21.1,"y":-3.2,"rotation":-57.84,"width":36,"height":39}},"cc_La_4":{"cc_La_4":{"x":17.03,"y":2.97,"rotation":-137.36,"width":36,"height":26}},"cc_La_7":{"cc_La_7":{"x":11.7,"y":3.24,"rotation":-96.6,"width":57,"height":29}},"cc_La_8":{"cc_La_8":{"x":46.64,"y":-3.72,"rotation":-77.83,"width":46,"height":95}},"cc_La_9":{"cc_La_9":{"x":31.94,"y":-1.99,"rotation":-58.94,"width":49,"height":61}},"cc_La_56":{"cc_La_56":{"x":4.64,"y":-1.8,"width":68,"height":38}},"cc_Ngo_1":{"cc_Ngo_1":{"x":24.78,"y":0.73,"rotation":-71.39,"width":41,"height":56}},"cc_Ngo_2":{"cc_Ngo_2":{"x":23.45,"y":-1.68,"rotation":-125.21,"width":44,"height":57}},"cc_Ngo_3":{"cc_Ngo_3":{"x":20.23,"y":1.32,"rotation":-60.62,"width":42,"height":53}},"cc_Ngo_4":{"cc_Ngo_4":{"x":30.79,"y":-0.13,"rotation":-92.55,"width":47,"height":71}},"hat_giongA":{"hat_giong1":{"width":19,"height":14}},"mamA":{"mam":{"x":27.82,"y":-0.56,"rotation":-90,"width":63,"height":63}}}}],"animations":{"Idle0":{"slots":{"cc_Body":{"attachment":[{"name":null}]},"cc_La_1":{"attachment":[{"name":null}]},"cc_La_2":{"attachment":[{"name":null}]},"cc_La_3":{"attachment":[{"name":null}]},"cc_La_7":{"attachment":[{"name":null}]},"cc_La_8":{"attachment":[{"name":null}]},"cc_La_9":{"attachment":[{"name":null}]},"cc_La_56":{"attachment":[{"name":null}]},"cc_Ngo_1":{"attachment":[{"name":null}]},"cc_Ngo_2":{"attachment":[{"name":null}]},"cc_Ngo_3":{"attachment":[{"name":null}]},"cc_Ngo_4":{"attachment":[{"name":null}]},"hat_giongA":{"attachment":[{"name":"hat_giong1"}]}},"bones":{"mamA":{"scale":[{"time":0.3333}]}}},"Idle1":{"slots":{"cc_Body":{"attachment":[{"name":null}]},"cc_La_1":{"attachment":[{"name":null}]},"cc_La_2":{"attachment":[{"name":null}]},"cc_La_3":{"attachment":[{"name":null}]},"cc_La_7":{"attachment":[{"name":null}]},"cc_La_8":{"attachment":[{"name":null}]},"cc_La_9":{"attachment":[{"name":null}]},"cc_La_56":{"attachment":[{"name":null}]},"cc_Ngo_1":{"attachment":[{"name":null}]},"cc_Ngo_2":{"attachment":[{"name":null}]},"cc_Ngo_3":{"attachment":[{"name":null}]},"cc_Ngo_4":{"attachment":[{"name":null}]},"mamA":{"attachment":[{"name":"mam"}]}},"bones":{"mamA":{"rotate":[{"angle":-3.81,"curve":0.25,"c3":0.75},{"time":0.4667,"angle":0.26,"curve":0.25,"c3":0.75},{"time":0.9333,"angle":-3.81}]}}},"Idle2":{"slots":{"cc_C1_La":{"attachment":[{"name":"cc_C1_La"}]},"cc_La_4":{"attachment":[{"name":"cc_La_4"}]},"cc_La_8":{"attachment":[{"name":null}]},"cc_Ngo_1":{"attachment":[{"name":null}]},"cc_Ngo_2":{"attachment":[{"name":null}]},"cc_Ngo_3":{"attachment":[{"name":null}]},"cc_Ngo_4":{"attachment":[{"name":null}]}},"bones":{"cc_La_4":{"rotate":[{"angle":3.29,"curve":0.34,"c2":0.36,"c3":0.757},{"time":0.6,"angle":15.13,"curve":0.25,"c3":0.75},{"time":1.4333,"curve":0.272,"c3":0.619,"c4":0.41},{"time":1.6667,"angle":3.29}],"translate":[{"x":12.14,"y":-7.94}],"scale":[{"x":0.908,"y":0.908}]},"cc_La_1":{"rotate":[{"angle":-1.79,"curve":0.381,"c2":0.55,"c3":0.742},{"time":0.3333,"curve":0.25,"c3":0.75},{"time":1.1667,"angle":-4.86,"curve":0.245,"c3":0.637,"c4":0.56},{"time":1.6667,"angle":-1.79}],"translate":[{"x":1.15,"y":-1.72}],"scale":[{"x":0.866,"y":0.866}]},"cc_La_7":{"rotate":[{"curve":0.25,"c3":0.75},{"time":0.8333,"angle":-2.97,"curve":0.25,"c3":0.75},{"time":1.6667}],"translate":[{"x":1.85,"y":-2.32}],"scale":[{"x":0.953,"y":0.953}]},"cc_La_8":{"rotate":[{"curve":0.25,"c3":0.75},{"time":0.8333,"angle":2.33,"curve":0.25,"c3":0.75},{"time":1.6667}],"scale":[{"x":0.635,"y":0.635}]},"cc_Body":{"scale":[{"x":0.892,"y":0.892}]},"cc_La_9":{"rotate":[{"curve":0.25,"c3":0.75},{"time":0.8333,"angle":3.83,"curve":0.25,"c3":0.75},{"time":1.6667}],"translate":[{"x":0.47,"y":2.8}],"scale":[{"x":0.879,"y":0.879}]},"cc_La_2":{"rotate":[{"curve":0.25,"c3":0.75},{"time":0.8333,"angle":2.33,"curve":0.25,"c3":0.75},{"time":1.6667}],"translate":[{"x":-1.78,"y":-3.56}],"scale":[{"x":0.86,"y":0.86}]},"cc_La_3":{"rotate":[{"curve":0.25,"c3":0.75},{"time":0.8333,"angle":-2.97,"curve":0.25,"c3":0.75},{"time":1.6667}],"translate":[{"x":-7.77,"y":-16.51}],"scale":[{"x":0.872,"y":0.872}]},"cc_C1_La":{"rotate":[{"angle":-2.73,"curve":0.25,"c3":0.75},{"time":0.8333,"angle":2.33,"curve":0.25,"c3":0.75},{"time":1.6667,"angle":-2.73}],"translate":[{"x":-1.35,"y":-4.59}],"scale":[{"x":0.991,"y":0.991}]}}},"Idle3":{"slots":{"cc_La_4":{"attachment":[{"name":"cc_La_4"}]}},"bones":{"cc_La_4":{"rotate":[{"angle":-2.43,"curve":0.356,"c2":0.42,"c3":0.756},{"time":0.5333,"curve":0.25,"c3":0.75},{"time":1.3667,"angle":-3.56,"curve":0.262,"c3":0.618,"c4":0.44},{"time":1.6667,"angle":-2.43}]},"cc_La_1":{"rotate":[{"angle":-1.04,"curve":0.382,"c2":0.58,"c3":0.734},{"time":0.2667,"curve":0.25,"c3":0.75},{"time":1.1,"angle":-3.89,"curve":0.243,"c3":0.651,"c4":0.61},{"time":1.6667,"angle":-1.04}]},"cc_La_7":{"rotate":[{"curve":0.25,"c3":0.75},{"time":0.8333,"angle":-4.19,"curve":0.25,"c3":0.75},{"time":1.6667}]},"cc_La_8":{"rotate":[{"curve":0.25,"c3":0.75},{"time":0.8333,"angle":3.21,"curve":0.25,"c3":0.75},{"time":1.6667}]},"cc_Ngo_4":{"rotate":[{"curve":0.25,"c3":0.75},{"time":0.8333,"angle":1.89,"curve":0.25,"c3":0.75},{"time":1.6667}]},"cc_Ngo_1":{"rotate":[{"curve":0.25,"c3":0.75},{"time":0.8333,"angle":1.81,"curve":0.25,"c3":0.75},{"time":1.6667}]},"cc_Ngo_2":{"rotate":[{"curve":0.25,"c3":0.75},{"time":0.8333,"angle":3.55,"curve":0.25,"c3":0.75},{"time":1.6667}],"translate":[{"curve":0.25,"c3":0.75},{"time":0.8333,"x":-0.65,"curve":0.25,"c3":0.75},{"time":1.6667}]},"cc_Ngo_3":{"rotate":[{"angle":-0.87,"curve":0.382,"c2":0.56,"c3":0.738},{"time":0.3,"curve":0.25,"c3":0.75},{"time":1.1333,"angle":-2.75,"curve":0.244,"c3":0.644,"c4":0.58},{"time":1.6667,"angle":-0.87}]},"cc_La_9":{"rotate":[{"angle":-2.43,"curve":0.356,"c2":0.42,"c3":0.756},{"time":0.5333,"curve":0.25,"c3":0.75},{"time":1.3667,"angle":-3.56,"curve":0.262,"c3":0.618,"c4":0.44},{"time":1.6667,"angle":-2.43}]},"cc_La_2":{"rotate":[{"curve":0.25,"c3":0.75},{"time":0.8333,"angle":3.21,"curve":0.25,"c3":0.75},{"time":1.6667}]},"cc_La_3":{"rotate":[{"curve":0.25,"c3":0.75},{"time":0.8333,"angle":-4.19,"curve":0.25,"c3":0.75},{"time":1.6667}]},"cc_C1_La":{"rotate":[{"curve":0.25,"c3":0.75},{"time":0.8333,"angle":3.21,"curve":0.25,"c3":0.75},{"time":1.6667}]}}},"ThuHoach":{"slots":{"cc_Body":{"color":[{"color":"ffffffff"},{"time":0.6667,"color":"ffffff00"}]},"cc_La_1":{"color":[{"color":"ffffffff"},{"time":0.6667,"color":"ffffff00"}]},"cc_La_2":{"color":[{"color":"ffffffff"},{"time":0.6667,"color":"ffffff00"}]},"cc_La_3":{"color":[{"color":"ffffffff"},{"time":0.6667,"color":"ffffff00"}]},"cc_La_4":{"color":[{"color":"ffffffff"},{"time":0.6667,"color":"ffffff00"}],"attachment":[{"name":"cc_La_4"}]},"cc_La_7":{"color":[{"color":"ffffffff"},{"time":0.6667,"color":"ffffff00"}]},"cc_La_8":{"color":[{"color":"ffffffff"},{"time":0.6667,"color":"ffffff00"}]},"cc_La_9":{"color":[{"color":"ffffffff"},{"time":0.6667,"color":"ffffff00"}]},"cc_La_56":{"color":[{"color":"ffffffff"},{"time":0.6667,"color":"ffffff00"}]},"cc_Ngo_1":{"attachment":[{"name":null}]},"cc_Ngo_2":{"attachment":[{"name":null}]},"cc_Ngo_3":{"attachment":[{"name":null}]},"cc_Ngo_4":{"attachment":[{"name":null}]}},"bones":{"cc_La_4":{"rotate":[{},{"time":0.6667,"angle":70.44}],"translate":[{},{"time":0.6667,"x":-3.72,"y":-26.66}]},"cc_La_1":{"rotate":[{},{"time":0.3,"angle":-14.32},{"time":0.6667,"angle":-28.5}],"translate":[{"curve":0.135,"c2":0.2,"c3":0.75},{"time":0.3,"x":2.48,"y":11.55,"curve":0.25,"c3":0.857,"c4":0.81},{"time":0.6667,"x":9.9,"y":-11.55}]},"cc_La_7":{"rotate":[{},{"time":0.6667,"angle":11.11}],"scale":[{},{"time":0.6667,"x":0.889,"y":0.889}]},"cc_La_8":{"rotate":[{},{"time":0.6667,"angle":-9.11}],"scale":[{},{"time":0.6667,"x":0.797,"y":0.948}]},"cc_Body":{"rotate":[{},{"time":0.6667,"angle":2.63}],"scale":[{},{"time":0.6667,"x":0.766}]},"cc_La_9":{"rotate":[{},{"time":0.6667,"angle":-14.98}],"scale":[{},{"time":0.6667,"x":0.703}]},"cc_La_2":{"rotate":[{},{"time":0.6667,"angle":-7.3}],"translate":[{},{"time":0.6667,"x":-3.8,"y":-19.19}]},"cc_La_3":{"rotate":[{},{"time":0.6667,"angle":28.77}],"translate":[{},{"time":0.6667,"x":-3.55,"y":-29.15}]}}},"Upgrade_01":{"slots":{"cc_Body":{"attachment":[{"name":null}]},"cc_La_1":{"attachment":[{"name":null}]},"cc_La_2":{"attachment":[{"name":null}]},"cc_La_3":{"attachment":[{"name":null}]},"cc_La_7":{"attachment":[{"name":null}]},"cc_La_8":{"attachment":[{"name":null}]},"cc_La_9":{"attachment":[{"name":null}]},"cc_La_56":{"attachment":[{"name":null}]},"cc_Ngo_1":{"attachment":[{"name":null}]},"cc_Ngo_2":{"attachment":[{"name":null}]},"cc_Ngo_3":{"attachment":[{"name":null}]},"cc_Ngo_4":{"attachment":[{"name":null}]},"hat_giongA":{"color":[{"color":"ffffffff"},{"time":0.4,"color":"ffffff00"}],"attachment":[{"name":"hat_giong1"}]},"mamA":{"color":[{"color":"ffffff00"},{"time":0.3333,"color":"ffffffff"}],"attachment":[{"name":"mam"}]}},"bones":{"mamA":{"rotate":[{"angle":-3.81}],"scale":[{"x":0.504,"y":0.504,"curve":0.16,"c2":0.23,"c3":0.75},{"time":0.6333,"x":1.022,"y":1.022,"curve":0.25,"c3":0.85,"c4":0.79},{"time":1}]}}},"Upgrade_12":{"slots":{"cc_Body":{"color":[{"color":"ffffff00"},{"time":0.9667,"color":"ffffffff"}]},"cc_C1_La":{"color":[{"color":"ffffff00"},{"time":0.7,"color":"ffffffff"}],"attachment":[{"name":"cc_C1_La"}]},"cc_La_1":{"color":[{"color":"ffffff00"},{"time":0.7,"color":"ffffffff"}]},"cc_La_2":{"color":[{"color":"ffffff00"},{"time":0.6667,"color":"ffffffff"}]},"cc_La_3":{"color":[{"color":"ffffff00"},{"time":0.9667,"color":"ffffffff"}]},"cc_La_4":{"color":[{"color":"ffffff00"},{"time":0.9667,"color":"ffffffff"}],"attachment":[{"name":"cc_La_4"}]},"cc_La_7":{"color":[{"color":"ffffff00"},{"time":0.5333,"color":"ffffffff"}]},"cc_La_8":{"attachment":[{"name":null}]},"cc_La_9":{"color":[{"color":"ffffff00"},{"time":0.9667,"color":"ffffffff"}]},"cc_La_56":{"color":[{"color":"ffffff00"},{"time":0.4,"color":"ffffffff"}]},"cc_Ngo_1":{"attachment":[{"name":null}]},"cc_Ngo_2":{"attachment":[{"name":null}]},"cc_Ngo_3":{"attachment":[{"name":null}]},"cc_Ngo_4":{"attachment":[{"name":null}]},"mamA":{"color":[{"color":"ffffffff"},{"time":1.2333,"color":"ffffff00"}],"attachment":[{"name":"mam"}]}},"bones":{"mamA":{"rotate":[{"angle":-1.54},{"time":1.5667,"angle":-1.7}],"scale":[{},{"time":1.5667,"x":1.602,"y":1.602}]},"cc_La_4":{"rotate":[{"angle":-0.61,"curve":0.25,"c3":0.75},{"time":1.3667,"angle":3.29}],"translate":[{"x":10.97,"y":-10.68,"curve":0.25,"c3":0.75},{"time":1.3667,"x":12.14,"y":-7.94}],"scale":[{"x":0.791,"y":0.791,"curve":0.25,"c3":0.75},{"time":1.3667,"x":0.908,"y":0.908}]},"cc_La_7":{"rotate":[{"curve":0.25,"c3":0.75},{"time":1.1667,"angle":4.4,"curve":0.25,"c3":0.75},{"time":2.3333}],"translate":[{"x":1.85,"y":-2.32}],"scale":[{"x":0.811,"y":0.811,"curve":0.25,"c3":0.75},{"time":1.1667,"x":0.953,"y":0.953}]},"cc_La_1":{"rotate":[{"angle":-1.79,"curve":0.25,"c3":0.75},{"time":1.3667,"angle":1.06,"curve":0.25,"c3":0.75},{"time":2.3333,"angle":-1.79}],"translate":[{"x":1.15,"y":-1.72}],"scale":[{"x":0.545,"y":0.866,"curve":0.25,"c3":0.75},{"time":1.3667,"x":0.894,"y":0.866,"curve":0.25,"c3":0.75},{"time":2.3333,"x":0.866,"y":0.866}]},"cc_Body":{"rotate":[{"curve":0.25,"c3":0.75},{"time":1.1333,"angle":0.3,"curve":0.25,"c3":0.75},{"time":2.3333}],"scale":[{"x":0.775,"y":0.775,"curve":0.25,"c3":0.75},{"time":1.1333,"x":0.933,"y":0.892,"curve":0.25,"c3":0.75},{"time":2.3333,"x":0.892,"y":0.892}]},"cc_La_9":{"rotate":[{"angle":28.25,"curve":0.203,"c2":0.32,"c3":0.75},{"time":1.7333,"angle":-1.57,"curve":0.25,"c3":0.75},{"time":2.3333}],"translate":[{"x":0.47,"y":2.8}],"scale":[{"x":0.879,"y":0.879}]},"cc_La_2":{"rotate":[{"angle":-17.68,"curve":0.25,"c3":0.75},{"time":1.3667,"angle":6.05,"curve":0.25,"c3":0.75},{"time":2.3333}],"translate":[{"x":-3.47,"y":-8.63,"curve":0.25,"c3":0.75},{"time":1.3667,"x":-1.78,"y":-3.56}],"scale":[{"x":0.86,"y":0.86}]},"cc_La_3":{"rotate":[{"angle":7.14,"curve":0.25,"c3":0.75},{"time":1.3667}],"translate":[{"x":-8.94,"y":-19.25,"curve":0.25,"c3":0.75},{"time":1.3667,"x":-7.77,"y":-16.51}],"scale":[{"x":0.698,"y":0.698,"curve":0.25,"c3":0.75},{"time":1.3667,"x":0.872,"y":0.872}]},"cc_C1_La":{"rotate":[{"angle":-2.73,"curve":0.25,"c3":0.75},{"time":1.3667,"angle":-3.43,"curve":0.25,"c3":0.75},{"time":2.3333,"angle":-2.73}],"translate":[{"x":-0.51,"y":-8.82,"curve":0.25,"c3":0.75},{"time":1.3667,"x":-1.35,"y":-4.59}],"scale":[{"x":0.991,"y":0.991,"curve":0.25,"c3":0.75},{"time":1.3667,"x":0.926,"y":0.991,"curve":0.25,"c3":0.75},{"time":2.3333,"x":0.991,"y":0.991}]},"cc_La_8":{"scale":[{"time":1.3667,"x":0.635,"y":0.635}]}}},"Upgrade_23":{"slots":{"cc_La_4":{"attachment":[{"name":"cc_La_4"}]},"cc_La_8":{"color":[{"color":"ffffff00"},{"time":0.3333,"color":"ffffffff"}]},"cc_Ngo_1":{"color":[{"color":"ffffff00"},{"time":0.3333,"color":"ffffffff"}]},"cc_Ngo_2":{"color":[{"color":"ffffff00","curve":"stepped"},{"time":0.3333,"color":"ffffff00"},{"time":0.6,"color":"ffffffff"}]},"cc_Ngo_3":{"color":[{"color":"ffffff00"},{"time":0.6667,"color":"ffffff18"},{"time":1,"color":"ffffffff"}]},"cc_Ngo_4":{"color":[{"color":"ffffff00"},{"time":0.6667,"color":"ffffffff"}]}},"bones":{"cc_La_4":{"rotate":[{"angle":3.29,"curve":0.16,"c2":0.41,"c3":0.75},{"time":1.3333,"angle":-6.46},{"time":1.8333}],"translate":[{"x":12.14,"y":-7.94,"curve":0.16,"c2":0.41,"c3":0.75},{"time":1.3333}],"scale":[{"x":0.908,"y":0.908,"curve":0.16,"c2":0.41,"c3":0.75},{"time":1.3333}]},"cc_La_1":{"rotate":[{"angle":-1.79,"curve":0.027,"c2":0.47,"c3":0.75},{"time":1.3333}],"translate":[{"x":1.15,"y":-1.72,"curve":0.027,"c2":0.47,"c3":0.75},{"time":1.3333}],"scale":[{"x":0.866,"y":0.866,"curve":0.027,"c2":0.47,"c3":0.75},{"time":1.3333}]},"cc_La_7":{"translate":[{"x":1.85,"y":-2.32,"curve":0.148,"c2":0.41,"c3":0.75},{"time":1.2}],"scale":[{"x":0.699,"y":0.723,"curve":0.148,"c2":0.41,"c3":0.75},{"time":1.2,"x":1.036,"y":1.036},{"time":1.6333,"x":0.987,"y":0.987},{"time":2}]},"cc_La_8":{"scale":[{"x":0.635,"y":0.635,"curve":0.148,"c2":0.41,"c3":0.75},{"time":1.2,"x":1.016,"y":1.016},{"time":1.6333,"x":0.987,"y":0.987},{"time":2}]},"cc_Ngo_4":{"rotate":[{"curve":0.148,"c2":0.41,"c3":0.75},{"time":1,"angle":-6.47,"curve":0.25,"c3":0.877,"c4":0.81},{"time":1.7,"angle":4.8,"curve":0.15,"c2":0.2,"c3":0.75},{"time":2.1667}],"translate":[{"x":2.66,"y":-26.94,"curve":0.148,"c2":0.41,"c3":0.75},{"time":1.3333}],"scale":[{"x":0.405,"y":0.405},{"time":1.3333}]},"cc_Ngo_1":{"rotate":[{"curve":0.148,"c2":0.41,"c3":0.75},{"time":1.3333,"angle":-1.97},{"time":2.1667}],"translate":[{"x":-0.29,"y":-3.02,"curve":0.148,"c2":0.41,"c3":0.75},{"time":1.3333,"x":0.32,"y":0.23},{"time":2.1667}],"scale":[{"x":0.318,"y":0.318,"curve":0.148,"c2":0.41,"c3":0.75},{"time":1.3333,"x":1.018,"y":1.018},{"time":2.1667}]},"cc_Ngo_2":{"rotate":[{"curve":0.148,"c2":0.41,"c3":0.75},{"time":1.3333,"angle":-0.65,"curve":0.25,"c3":0.852,"c4":0.78},{"time":1.8333}],"translate":[{"x":14.53,"y":-21.39,"curve":0.148,"c2":0.41,"c3":0.75},{"time":1.3333,"y":-0.41,"curve":0.25,"c3":0.852,"c4":0.78},{"time":1.8333}],"scale":[{"x":0.329,"y":0.329,"curve":0.148,"c2":0.41,"c3":0.75},{"time":1.3333,"x":1.031,"y":1.031,"curve":0.25,"c3":0.852,"c4":0.78},{"time":1.8333}]},"cc_Ngo_3":{"rotate":[{"curve":0.148,"c2":0.41,"c3":0.75},{"time":0.7333,"angle":8.82,"curve":0.25,"c3":0.75},{"time":1.6,"angle":-2.8,"curve":0.25,"c3":0.75},{"time":2.1667}],"translate":[{"x":-5.07,"y":-33.78,"curve":0.148,"c2":0.41,"c3":0.75},{"time":1.3333}],"scale":[{"x":0.334,"y":0.334,"curve":0.148,"c2":0.41,"c3":0.75},{"time":1.3333}]},"cc_Body":{"scale":[{"x":0.892,"y":0.892},{"time":1.3333}]},"cc_La_9":{"rotate":[{"curve":0.153,"c2":0.41,"c3":0.75},{"time":1.3333,"angle":-0.78},{"time":1.8333}],"translate":[{"x":0.47,"y":2.8,"curve":0.153,"c2":0.41,"c3":0.75},{"time":1.3333}],"scale":[{"x":0.879,"y":0.879,"curve":0.153,"c2":0.41,"c3":0.75},{"time":1.3333}]},"cc_La_2":{"translate":[{"x":-1.78,"y":-3.56,"curve":0.25,"c3":0.75},{"time":1.2}],"scale":[{"x":0.86,"y":0.86,"curve":0.142,"c2":0.3,"c3":0.75},{"time":1.2,"x":1.036,"y":1.036},{"time":1.6333,"x":0.987,"y":0.987},{"time":2}]},"cc_La_3":{"translate":[{"x":-7.77,"y":-16.51,"curve":0.155,"c2":0.4,"c3":0.75},{"time":1.2,"x":-0.33,"y":-0.33},{"time":1.6333}],"scale":[{"x":0.872,"y":0.872,"curve":0.155,"c2":0.4,"c3":0.75},{"time":1.2,"x":1.036,"y":1.036},{"time":1.6333,"x":0.987,"y":0.987},{"time":2}]},"cc_C1_La":{"rotate":[{"angle":-2.73,"curve":0.25,"c3":0.75},{"time":1.2}],"translate":[{"x":-1.35,"y":-4.59,"curve":0.25,"c3":0.75},{"time":1.2}],"scale":[{"x":0.991,"y":0.991,"curve":0.25,"c3":0.75},{"time":1.2,"x":1.036,"y":1.036},{"time":1.6333,"x":0.987,"y":0.987},{"time":2}]}}}}}